brainles_preprocessing/__init__.py
brainles_preprocessing/brain_extraction/__init__.py
brainles_preprocessing/brain_extraction/brain_extractor.py
brainles_preprocessing/brain_extraction/synthstrip.py
brainles_preprocessing/brats/__init__.py
brainles_preprocessing/brats/t1_centric.py
brainles_preprocessing/brats/t1c_centric.py
brainles_preprocessing/cli.py
brainles_preprocessing/constants.py
brainles_preprocessing/defacing/__init__.py
brainles_preprocessing/defacing/defacer.py
brainles_preprocessing/defacing/quickshear/__init__.py
brainles_preprocessing/defacing/quickshear/nipy_quickshear.py
brainles_preprocessing/defacing/quickshear/quickshear.py
brainles_preprocessing/modality.py
brainles_preprocessing/n4_bias_correction/__init__.py
brainles_preprocessing/n4_bias_correction/n4_bias_corrector.py
brainles_preprocessing/n4_bias_correction/sitk/__init__.py
brainles_preprocessing/n4_bias_correction/sitk/sitk_n4_bias_corrector.py
brainles_preprocessing/normalization/__init__.py
brainles_preprocessing/normalization/normalizer_base.py
brainles_preprocessing/normalization/percentile_normalizer.py
brainles_preprocessing/normalization/windowing_normalizer.py
brainles_preprocessing/preprocessor/__init__.py
brainles_preprocessing/preprocessor/atlas_centric_preprocessor.py
brainles_preprocessing/preprocessor/native_space_preprocessor.py
brainles_preprocessing/preprocessor/preprocessor.py
brainles_preprocessing/registration/ANTs/ANTs.py
brainles_preprocessing/registration/ANTs/TODO_ANTs_parameters.py
brainles_preprocessing/registration/ANTs/__init__.py
brainles_preprocessing/registration/__init__.py
brainles_preprocessing/registration/elastix/__init__.py
brainles_preprocessing/registration/elastix/elastix.py
brainles_preprocessing/registration/greedy/__init__.py
brainles_preprocessing/registration/greedy/greedy.py
brainles_preprocessing/registration/niftyreg/__init__.py
brainles_preprocessing/registration/niftyreg/niftyreg.py
brainles_preprocessing-0.6.9.dist-info/METADATA
brainles_preprocessing-0.6.9.dist-info/WHEEL
brainles_preprocessing-0.6.9.dist-info/entry_points.txt
brainles_preprocessing-0.6.9.dist-info/licenses/LICENSE
brainles_preprocessing-0.6.9.dist-info/RECORD
