Metadata-Version: 2.4
Name: brainles_preprocessing
Version: 0.6.9
Summary: Tool for preprocessing tasks in biomedical imaging, with a focus on (but not limited to) multi-modal brain MRI
License: Apache-2.0
License-File: LICENSE
Keywords: brain tumor,glioma,BraTS,skullstripping,brain extraction
Author: Florian Kofler
Author-email: florian.kofler@tum.de
Maintainer: Florian Kofler
Maintainer-email: florian.kofler@tum.de
Requires-Python: >=3.10,<4.0
Classifier: License :: OSI Approved :: Apache Software License
Classifier: Operating System :: OS Independent
Classifier: Programming Language :: Python :: 3
Classifier: Programming Language :: Python :: 3.10
Classifier: Programming Language :: Python :: 3.11
Classifier: Programming Language :: Python :: 3.12
Classifier: Programming Language :: Python :: 3.13
Classifier: Programming Language :: Python :: 3.14
Provides-Extra: all
Provides-Extra: itk-elastix
Provides-Extra: picsl-greedy
Provides-Extra: synthstrip
Requires-Dist: antspyx (>=0.5.4,<1.0.0)
Requires-Dist: auxiliary (>=0.3.1)
Requires-Dist: brainles_hd_bet (>=0.0.10,<1.0.0)
Requires-Dist: itk-elastix (>=0.20.0,<0.21.0) ; extra == "all" or extra == "itk-elastix"
Requires-Dist: loguru (>=0.7.3,<0.8.0)
Requires-Dist: nibabel (>=3.2.1)
Requires-Dist: nipreps-synthstrip (>=0.0.1,<0.0.2) ; extra == "all" or extra == "synthstrip"
Requires-Dist: numpy (>=1.23.0,<2.0.0)
Requires-Dist: picsl_greedy (>=0.0.6,<0.0.7) ; extra == "all" or extra == "picsl-greedy"
Requires-Dist: rich (>=13.6.0,<14.0.0)
Requires-Dist: scipy (>=1.14,<2.0)
Requires-Dist: simpleitk (>=2.2.1)
Requires-Dist: tqdm (>=4.64.1,<5.0.0)
Requires-Dist: ttictoc (>=0.5.6,<0.6.0)
Requires-Dist: typer (>=0.15.0,<0.16.0)
Project-URL: Repository, https://github.com/BrainLesion/preprocessing
